[
  {
    "Attack": 82,
    "Defense": 83,
    "HP": 80,
    "Special_Atk": 100,
    "Special_Def": 100,
    "Speed": 80,
    "Total": 525,
    "Type1": "Grass",
    "Type2": "Poison"
  },
  {
    "Attack": 83,
    "Defense": 100,
    "HP": 79,
    "Special_Atk": 85,
    "Special_Def": 105,
    "Speed": 78,
    "Total": 530,
    "Type1": "Water",
    "Type2": "Water"
  },
  {
    "Attack": 55,
    "Defense": 40,
    "HP": 35,
    "Special_Atk": 50,
    "Special_Def": 50,
    "Speed": 90,
    "Total": 320,
    "Type1": "Electric",
    "Type2": "Electric"
  },
  {
    "Attack": 80,
    "Defense": 35,
    "HP": 40,
    "Special_Atk": 35,
    "Special_Def": 45,
    "Speed": 70,
    "Total": 305,
    "Type1": "Fighting",
    "Type2": "Fighting"
  },
  {
    "Attack": 70,
    "Defense": 45,
    "HP": 55,
    "Special_Atk": 70,
    "Special_Def": 50,
    "Speed": 60,
    "Total": 350,
    "Type1": "Fire",
    "Type2": "Fire"
  },
  {
    "Attack": 82,
    "Defense": 100,
    "HP": 80,
    "Special_Atk": 83,
    "Special_Def": 100,
    "Speed": 80,
    "Total": 525,
    "Type1": "Grass",
    "Type2": "Grass"
  },
  {
    "Attack": 84,
    "Defense": 78,
    "HP": 78,
    "Special_Atk": 109,
    "Special_Def": 85,
    "Speed": 100,
    "Total": 534,
    "Type1": "Fire",
    "Type2": "Flying"
  },
  {
    "Attack": 100,
    "Defense": 115,
    "HP": 70,
    "Special_Atk": 30,
    "Special_Def": 65,
    "Speed": 30,
    "Total": 410,
    "Type1": "Rock",
    "Type2": "Rock"
  },
  {
    "Attack": 55,
    "Defense": 35,
    "HP": 35,
    "Special_Atk": 30,
    "Special_Def": 30,
    "Speed": 35,
    "Total": 220,
    "Type1": "Dark",
    "Type2": "Dark"
  },
  {
    "Attack": 45,
    "Defense": 50,
    "HP": 60,
    "Special_Atk": 90,
    "Special_Def": 80,
    "Speed": 70,
    "Total": 395,
    "Type1": "Bug",
    "Type2": "Flying"
  },
  {
    "Attack": 75,
    "Defense": 60,
    "HP": 45,
    "Special_Atk": 40,
    "Special_Def": 30,
    "Speed": 50,
    "Total": 300,
    "Type1": "Dragon",
    "Type2": "Dragon"
  },
  {
    "Attack": 50,
    "Defense": 100,
    "HP": 80,
    "Special_Atk": 100,
    "Special_Def": 200,
    "Speed": 50,
    "Total": 580,
    "Type1": "Ice",
    "Type2": "Ice"
  },
  {
    "Attack": 66,
    "Defense": 44,
    "HP": 55,
    "Special_Atk": 44,
    "Special_Def": 56,
    "Speed": 85,
    "Total": 350,
    "Type1": "Normal",
    "Type2": "Normal"
  },
  {
    "Attack": 100,
    "Defense": 80,
    "HP": 79,
    "Special_Atk": 110,
    "Special_Def": 90,
    "Speed": 121,
    "Total": 580,
    "Type1": "Flying",
    "Type2": "Flying"
  },
  {
    "Attack": 90,
    "Defense": 65,
    "HP": 68,
    "Special_Atk": 50,
    "Special_Def": 55,
    "Speed": 82,
    "Total": 410,
    "Type1": "Ground",
    "Type2": "Dragon"
  },
  {
    "Attack": 95,
    "Defense": 115,
    "HP": 55,
    "Special_Atk": 45,
    "Special_Def": 45,
    "Speed": 35,
    "Total": 390,
    "Type1": "Ground",
    "Type2": "Rock"
  },
  {
    "Attack": 35,
    "Defense": 30,
    "HP": 40,
    "Special_Atk": 20,
    "Special_Def": 20,
    "Speed": 50,
    "Total": 195,
    "Type1": "Bug",
    "Type2": "Poison"
  },
  {
    "Attack": 45,
    "Defense": 40,
    "HP": 40,
    "Special_Atk": 35,
    "Special_Def": 35,
    "Speed": 56,
    "Total": 251,
    "Type1": "Normal",
    "Type2": "Flying"
  },
  {
    "Attack": 56,
    "Defense": 35,
    "HP": 30,
    "Special_Atk": 25,
    "Special_Def": 35,
    "Speed": 72,
    "Total": 253,
    "Type1": "Dark",
    "Type2": "Normal"
  },
  {
    "Attack": 85,
    "Defense": 50,
    "HP": 60,
    "Special_Atk": 95,
    "Special_Def": 85,
    "Speed": 110,
    "Total": 485,
    "Type1": "Electric",
    "Type2": "Psychic"
  },
  {
    "Attack": 67,
    "Defense": 75,
    "HP": 73,
    "Special_Atk": 81,
    "Special_Def": 100,
    "Speed": 109,
    "Total": 505,
    "Type1": "Ice",
    "Type2": "Fairy"
  },
  {
    "Attack": 75,
    "Defense": 85,
    "HP": 50,
    "Special_Atk": 20,
    "Special_Def": 30,
    "Speed": 40,
    "Total": 300,
    "Type1": "Ground",
    "Type2": "Ground"
  },
  {
    "Attack": 47,
    "Defense": 52,
    "HP": 55,
    "Special_Atk": 40,
    "Special_Def": 40,
    "Speed": 41,
    "Total": 275,
    "Type1": "Poison",
    "Type2": "Poison"
  },
  {
    "Attack": 75,
    "Defense": 90,
    "HP": 50,
    "Special_Atk": 10,
    "Special_Def": 35,
    "Speed": 40,
    "Total": 300,
    "Type1": "Ice",
    "Type2": "Steel"
  },
  {
    "Attack": 92,
    "Defense": 87,
    "HP": 90,
    "Special_Atk": 75,
    "Special_Def": 85,
    "Speed": 76,
    "Total": 505,
    "Type1": "Poison",
    "Type2": "Ground"
  },
  {
    "Attack": 45,
    "Defense": 20,
    "HP": 115,
    "Special_Atk": 45,
    "Special_Def": 25,
    "Speed": 20,
    "Total": 270,
    "Type1": "Normal",
    "Type2": "Fairy"
  },
  {
    "Attack": 45,
    "Defense": 35,
    "HP": 40,
    "Special_Atk": 30,
    "Special_Def": 40,
    "Speed": 55,
    "Total": 245,
    "Type1": "Poison",
    "Type2": "Flying"
  },
  {
    "Attack": 70,
    "Defense": 55,
    "HP": 35,
    "Special_Atk": 45,
    "Special_Def": 55,
    "Speed": 25,
    "Total": 285,
    "Type1": "Bug",
    "Type2": "Grass"
  },
  {
    "Attack": 55,
    "Defense": 30,
    "HP": 10,
    "Special_Atk": 35,
    "Special_Def": 45,
    "Speed": 90,
    "Total": 265,
    "Type1": "Ground",
    "Type2": "Steel"
  },
  {
    "Attack": 65,
    "Defense": 55,
    "HP": 50,
    "Special_Atk": 40,
    "Special_Def": 40,
    "Speed": 40,
    "Total": 290,
    "Type1": "Steel",
    "Type2": "Steel"
  },
  {
    "Attack": 20,
    "Defense": 15,
    "HP": 25,
    "Special_Atk": 105,
    "Special_Def": 55,
    "Speed": 90,
    "Total": 310,
    "Type1": "Psychic",
    "Type2": "Psychic"
  },
  {
    "Attack": 75,
    "Defense": 110,
    "HP": 95,
    "Special_Atk": 100,
    "Special_Def": 80,
    "Speed": 30,
    "Total": 490,
    "Type1": "Water",
    "Type2": "Psychic"
  },
  {
    "Attack": 75,
    "Defense": 45,
    "HP": 60,
    "Special_Atk": 65,
    "Special_Def": 50,
    "Speed": 55,
    "Total": 350,
    "Type1": "Fire",
    "Type2": "Rock"
  },
  {
    "Attack": 95,
    "Defense": 95,
    "HP": 90,
    "Special_Atk": 70,
    "Special_Def": 90,
    "Speed": 70,
    "Total": 510,
    "Type1": "Water",
    "Type2": "Fighting"
  },
  {
    "Attack": 42,
    "Defense": 118,
    "HP": 30,
    "Special_Atk": 42,
    "Special_Def": 88,
    "Speed": 30,
    "Total": 350,
    "Type1": "Steel",
    "Type2": "Rock"
  },
  {
    "Attack": 40,
    "Defense": 35,
    "HP": 40,
    "Special_Atk": 50,
    "Special_Def": 100,
    "Speed": 70,
    "Total": 335,
    "Type1": "Poison",
    "Type2": "Water"
  },
  {
    "Attack": 80,
    "Defense": 100,
    "HP": 40,
    "Special_Atk": 30,
    "Special_Def": 30,
    "Speed": 20,
    "Total": 300,
    "Type1": "Rock",
    "Type2": "Electric"
  },
  {
    "Attack": 100,
    "Defense": 70,
    "HP": 65,
    "Special_Atk": 80,
    "Special_Def": 80,
    "Speed": 105,
    "Total": 500,
    "Type1": "Psychic",
    "Type2": "Fairy"
  },
  {
    "Attack": 95,
    "Defense": 180,
    "HP": 50,
    "Special_Atk": 85,
    "Special_Def": 45,
    "Speed": 70,
    "Total": 525,
    "Type1": "Water",
    "Type2": "Ice"
  },
  {
    "Attack": 65,
    "Defense": 60,
    "HP": 60,
    "Special_Atk": 130,
    "Special_Def": 75,
    "Speed": 110,
    "Total": 500,
    "Type1": "Ghost",
    "Type2": "Poison"
  },
  {
    "Attack": 125,
    "Defense": 100,
    "HP": 65,
    "Special_Atk": 55,
    "Special_Def": 70,
    "Speed": 85,
    "Total": 500,
    "Type1": "Bug",
    "Type2": "Bug"
  },
  {
    "Attack": 105,
    "Defense": 85,
    "HP": 95,
    "Special_Atk": 125,
    "Special_Def": 75,
    "Speed": 45,
    "Total": 530,
    "Type1": "Grass",
    "Type2": "Dragon"
  },
  {
    "Attack": 95,
    "Defense": 85,
    "HP": 95,
    "Special_Atk": 125,
    "Special_Def": 75,
    "Speed": 55,
    "Total": 530,
    "Type1": "Grass",
    "Type2": "Psychic"
  },
  {
    "Attack": 80,
    "Defense": 110,
    "HP": 60,
    "Special_Atk": 50,
    "Special_Def": 80,
    "Speed": 45,
    "Total": 425,
    "Type1": "Fire",
    "Type2": "Ghost"
  },
  {
    "Attack": 90,
    "Defense": 120,
    "HP": 65,
    "Special_Atk": 85,
    "Special_Def": 70,
    "Speed": 60,
    "Total": 490,
    "Type1": "Poison",
    "Type2": "Fairy"
  },
  {
    "Attack": 80,
    "Defense": 50,
    "HP": 80,
    "Special_Atk": 40,
    "Special_Def": 50,
    "Speed": 25,
    "Total": 325,
    "Type1": "Dark",
    "Type2": "Poison"
  },
  {
    "Attack": 30,
    "Defense": 50,
    "HP": 40,
    "Special_Atk": 55,
    "Special_Def": 55,
    "Speed": 100,
    "Total": 330,
    "Type1": "Electric",
    "Type2": "Grass"
  },
  {
    "Attack": 125,
    "Defense": 79,
    "HP": 95,
    "Special_Atk": 60,
    "Special_Def": 100,
    "Speed": 81,
    "Total": 540,
    "Type1": "Water",
    "Type2": "Flying"
  },
  {
    "Attack": 25,
    "Defense": 28,
    "HP": 50,
    "Special_Atk": 45,
    "Special_Def": 55,
    "Speed": 15,
    "Total": 218,
    "Type1": "Fairy",
    "Type2": "Fairy"
  },
  {
    "Attack": 105,
    "Defense": 65,
    "HP": 80,
    "Special_Atk": 60,
    "Special_Def": 75,
    "Speed": 130,
    "Total": 515,
    "Type1": "Rock",
    "Type2": "Flying"
  },
  {
    "Attack": 85,
    "Defense": 85,
    "HP": 90,
    "Special_Atk": 125,
    "Special_Def": 100,
    "Speed": 95,
    "Total": 580,
    "Type1": "Psychic",
    "Type2": "Flying"
  },
  {
    "Attack": 65,
    "Defense": 65,
    "HP": 50,
    "Special_Atk": 90,
    "Special_Def": 90,
    "Speed": 100,
    "Total": 460,
    "Type1": "Psychic",
    "Type2": "Ice"
  },
  {
    "Attack": 60,
    "Defense": 60,
    "HP": 60,
    "Special_Atk": 85,
    "Special_Def": 85,
    "Speed": 85,
    "Total": 435,
    "Type1": "Ghost",
    "Type2": "Ghost"
  },
  {
    "Attack": 115,
    "Defense": 105,
    "HP": 60,
    "Special_Atk": 65,
    "Special_Def": 70,
    "Speed": 80,
    "Total": 495,
    "Type1": "Water",
    "Type2": "Rock"
  },
  {
    "Attack": 85,
    "Defense": 100,
    "HP": 90,
    "Special_Atk": 95,
    "Special_Def": 125,
    "Speed": 85,
    "Total": 580,
    "Type1": "Ice",
    "Type2": "Flying"
  },
  {
    "Attack": 125,
    "Defense": 90,
    "HP": 90,
    "Special_Atk": 85,
    "Special_Def": 90,
    "Speed": 100,
    "Total": 580,
    "Type1": "Fighting",
    "Type2": "Flying"
  },
  {
    "Attack": 90,
    "Defense": 85,
    "HP": 90,
    "Special_Atk": 125,
    "Special_Def": 90,
    "Speed": 100,
    "Total": 580,
    "Type1": "Electric",
    "Type2": "Flying"
  },
  {
    "Attack": 85,
    "Defense": 90,
    "HP": 90,
    "Special_Atk": 100,
    "Special_Def": 125,
    "Speed": 90,
    "Total": 580,
    "Type1": "Dark",
    "Type2": "Flying"
  },
  {
    "Attack": 134,
    "Defense": 95,
    "HP": 91,
    "Special_Atk": 100,
    "Special_Def": 100,
    "Speed": 80,
    "Total": 600,
    "Type1": "Flying",
    "Type2": "Dragon"
  },
  {
    "Attack": 38,
    "Defense": 38,
    "HP": 75,
    "Special_Atk": 56,
    "Special_Def": 56,
    "Speed": 67,
    "Total": 330,
    "Type1": "Electric",
    "Type2": "Water"
  },
  {
    "Attack": 40,
    "Defense": 85,
    "HP": 55,
    "Special_Atk": 80,
    "Special_Def": 105,
    "Speed": 40,
    "Total": 405,
    "Type1": "Fairy",
    "Type2": "Flying"
  },
  {
    "Attack": 50,
    "Defense": 80,
    "HP": 100,
    "Special_Atk": 60,
    "Special_Def": 80,
    "Speed": 50,
    "Total": 420,
    "Type1": "Water",
    "Type2": "Fairy"
  },
  {
    "Attack": 130,
    "Defense": 100,
    "HP": 70,
    "Special_Atk": 55,
    "Special_Def": 80,
    "Speed": 65,
    "Total": 500,
    "Type1": "Bug",
    "Type2": "Steel"
  },
  {
    "Attack": 10,
    "Defense": 230,
    "HP": 20,
    "Special_Atk": 10,
    "Special_Def": 230,
    "Speed": 5,
    "Total": 505,
    "Type1": "Rock",
    "Type2": "Bug"
  },
  {
    "Attack": 35,
    "Defense": 40,
    "HP": 35,
    "Special_Atk": 35,
    "Special_Def": 55,
    "Speed": 50,
    "Total": 250,
    "Type1": "Grass",
    "Type2": "Flying"
  },
  {
    "Attack": 45,
    "Defense": 45,
    "HP": 55,
    "Special_Atk": 25,
    "Special_Def": 25,
    "Speed": 15,
    "Total": 210,
    "Type1": "Water",
    "Type2": "Ground"
  },
  {
    "Attack": 65,
    "Defense": 80,
    "HP": 95,
    "Special_Atk": 110,
    "Special_Def": 110,
    "Speed": 30,
    "Total": 490,
    "Type1": "Poison",
    "Type2": "Psychic"
  },
  {
    "Attack": 80,
    "Defense": 65,
    "HP": 70,
    "Special_Atk": 90,
    "Special_Def": 65,
    "Speed": 85,
    "Total": 455,
    "Type1": "Normal",
    "Type2": "Psychic"
  },
  {
    "Attack": 75,
    "Defense": 105,
    "HP": 65,
    "Special_Atk": 35,
    "Special_Def": 65,
    "Speed": 85,
    "Total": 430,
    "Type1": "Ground",
    "Type2": "Flying"
  },
  {
    "Attack": 125,
    "Defense": 75,
    "HP": 80,
    "Special_Atk": 40,
    "Special_Def": 95,
    "Speed": 85,
    "Total": 500,
    "Type1": "Bug",
    "Type2": "Fighting"
  },
  {
    "Attack": 95,
    "Defense": 55,
    "HP": 55,
    "Special_Atk": 35,
    "Special_Def": 75,
    "Speed": 115,
    "Total": 430,
    "Type1": "Dark",
    "Type2": "Ice"
  },
  {
    "Attack": 95,
    "Defense": 95,
    "HP": 75,
    "Special_Atk": 95,
    "Special_Def": 95,
    "Speed": 85,
    "Total": 540,
    "Type1": "Water",
    "Type2": "Dragon"
  },
  {
    "Attack": 134,
    "Defense": 110,
    "HP": 100,
    "Special_Atk": 95,
    "Special_Def": 100,
    "Speed": 61,
    "Total": 600,
    "Type1": "Rock",
    "Type2": "Dark"
  },
  {
    "Attack": 60,
    "Defense": 30,
    "HP": 45,
    "Special_Atk": 80,
    "Special_Def": 50,
    "Speed": 65,
    "Total": 330,
    "Type1": "Fire",
    "Type2": "Dark"
  },
  {
    "Attack": 80,
    "Defense": 140,
    "HP": 65,
    "Special_Atk": 40,
    "Special_Def": 70,
    "Speed": 70,
    "Total": 465,
    "Type1": "Flying",
    "Type2": "Steel"
  },
  {
    "Attack": 95,
    "Defense": 55,
    "HP": 55,
    "Special_Atk": 35,
    "Special_Def": 75,
    "Speed": 115,
    "Total": 430,
    "Type1": "Poison",
    "Type2": "Fighting"
  },
  {
    "Attack": 50,
    "Defense": 40,
    "HP": 50,
    "Special_Atk": 30,
    "Special_Def": 30,
    "Speed": 50,
    "Total": 250,
    "Type1": "Ice",
    "Type2": "Ground"
  },
  {
    "Attack": 120,
    "Defense": 70,
    "HP": 80,
    "Special_Atk": 110,
    "Special_Def": 70,
    "Speed": 80,
    "Total": 530,
    "Type1": "Fire",
    "Type2": "Fighting"
  },
  {
    "Attack": 70,
    "Defense": 70,
    "HP": 80,
    "Special_Atk": 90,
    "Special_Def": 100,
    "Speed": 70,
    "Total": 480,
    "Type1": "Water",
    "Type2": "Grass"
  },
  {
    "Attack": 100,
    "Defense": 60,
    "HP": 90,
    "Special_Atk": 90,
    "Special_Def": 60,
    "Speed": 80,
    "Total": 480,
    "Type1": "Grass",
    "Type2": "Dark"
  },
  {
    "Attack": 90,
    "Defense": 45,
    "HP": 1,
    "Special_Atk": 30,
    "Special_Def": 30,
    "Speed": 40,
    "Total": 236,
    "Type1": "Bug",
    "Type2": "Ghost"
  },
  {
    "Attack": 75,
    "Defense": 75,
    "HP": 50,
    "Special_Atk": 65,
    "Special_Def": 65,
    "Speed": 50,
    "Total": 380,
    "Type1": "Ghost",
    "Type2": "Dark"
  },
  {
    "Attack": 85,
    "Defense": 85,
    "HP": 50,
    "Special_Atk": 55,
    "Special_Def": 55,
    "Speed": 50,
    "Total": 380,
    "Type1": "Fairy",
    "Type2": "Steel"
  },
  {
    "Attack": 40,
    "Defense": 55,
    "HP": 30,
    "Special_Atk": 40,
    "Special_Def": 55,
    "Speed": 60,
    "Total": 280,
    "Type1": "Psychic",
    "Type2": "Fighting"
  },
  {
    "Attack": 130,
    "Defense": 80,
    "HP": 60,
    "Special_Atk": 60,
    "Special_Def": 60,
    "Speed": 70,
    "Total": 460,
    "Type1": "Grass",
    "Type2": "Fighting"
  },
  {
    "Attack": 45,
    "Defense": 90,
    "HP": 31,
    "Special_Atk": 30,
    "Special_Def": 30,
    "Speed": 40,
    "Total": 266,
    "Type1": "Bug",
    "Type2": "Ground"
  },
  {
    "Attack": 90,
    "Defense": 20,
    "HP": 45,
    "Special_Atk": 65,
    "Special_Def": 20,
    "Speed": 65,
    "Total": 305,
    "Type1": "Water",
    "Type2": "Dark"
  },
  {
    "Attack": 81,
    "Defense": 97,
    "HP": 86,
    "Special_Atk": 81,
    "Special_Def": 107,
    "Speed": 43,
    "Total": 495,
    "Type1": "Rock",
    "Type2": "Grass"
  },
  {
    "Attack": 60,
    "Defense": 40,
    "HP": 60,
    "Special_Atk": 65,
    "Special_Def": 45,
    "Speed": 35,
    "Total": 305,
    "Type1": "Fire",
    "Type2": "Ground"
  },
  {
    "Attack": 55,
    "Defense": 65,
    "HP": 90,
    "Special_Atk": 95,
    "Special_Def": 85,
    "Speed": 70,
    "Total": 460,
    "Type1": "Rock",
    "Type2": "Psychic"
  },
  {
    "Attack": 40,
    "Defense": 55,
    "HP": 40,
    "Special_Atk": 40,
    "Special_Def": 70,
    "Speed": 55,
    "Total": 300,
    "Type1": "Ground",
    "Type2": "Psychic"
  },
  {
    "Attack": 80,
    "Defense": 90,
    "HP": 80,
    "Special_Atk": 110,
    "Special_Def": 130,
    "Speed": 110,
    "Total": 600,
    "Type1": "Psychic",
    "Type2": "Dragon"
  },
  {
    "Attack": 135,
    "Defense": 130,
    "HP": 80,
    "Special_Atk": 95,
    "Special_Def": 90,
    "Speed": 70,
    "Total": 600,
    "Type1": "Psychic",
    "Type2": "Steel"
  },
  {
    "Attack": 109,
    "Defense": 105,
    "HP": 95,
    "Special_Atk": 75,
    "Special_Def": 85,
    "Speed": 56,
    "Total": 525,
    "Type1": "Grass",
    "Type2": "Ground"
  },
  {
    "Attack": 86,
    "Defense": 88,
    "HP": 84,
    "Special_Atk": 111,
    "Special_Def": 101,
    "Speed": 60,
    "Total": 530,
    "Type1": "Water",
    "Type2": "Steel"
  },
  {
    "Attack": 85,
    "Defense": 60,
    "HP": 79,
    "Special_Atk": 55,
    "Special_Def": 60,
    "Speed": 71,
    "Total": 410,
    "Type1": "Normal",
    "Type2": "Water"
  },
  {
    "Attack": 80,
    "Defense": 44,
    "HP": 150,
    "Special_Atk": 90,
    "Special_Def": 54,
    "Speed": 80,
    "Total": 498,
    "Type1": "Ghost",
    "Type2": "Flying"
  },
  {
    "Attack": 110,
    "Defense": 70,
    "HP": 70,
    "Special_Atk": 115,
    "Special_Def": 70,
    "Speed": 90,
    "Total": 525,
    "Type1": "Fighting",
    "Type2": "Steel"
  },
  {
    "Attack": 62,
    "Defense": 50,
    "HP": 60,
    "Special_Atk": 62,
    "Special_Def": 60,
    "Speed": 40,
    "Total": 334,
    "Type1": "Grass",
    "Type2": "Ice"
  },
  {
    "Attack": 80,
    "Defense": 70,
    "HP": 70,
    "Special_Atk": 80,
    "Special_Def": 70,
    "Speed": 110,
    "Total": 480,
    "Type1": "Ice",
    "Type2": "Ghost"
  },
  {
    "Attack": 65,
    "Defense": 107,
    "HP": 50,
    "Special_Atk": 105,
    "Special_Def": 107,
    "Speed": 86,
    "Total": 520,
    "Type1": "Electric",
    "Type2": "Fire"
  },
  {
    "Attack": 90,
    "Defense": 106,
    "HP": 91,
    "Special_Atk": 130,
    "Special_Def": 106,
    "Speed": 77,
    "Total": 600,
    "Type1": "Fire",
    "Type2": "Steel"
  },
  {
    "Attack": 120,
    "Defense": 100,
    "HP": 150,
    "Special_Atk": 120,
    "Special_Def": 100,
    "Speed": 90,
    "Total": 680,
    "Type1": "Ghost",
    "Type2": "Dragon"
  },
  {
    "Attack": 70,
    "Defense": 115,
    "HP": 70,
    "Special_Atk": 130,
    "Special_Def": 90,
    "Speed": 60,
    "Total": 535,
    "Type1": "Electric",
    "Type2": "Steel"
  },
  {
    "Attack": 65,
    "Defense": 107,
    "HP": 50,
    "Special_Atk": 105,
    "Special_Def": 107,
    "Speed": 86,
    "Total": 520,
    "Type1": "Electric",
    "Type2": "Ice"
  },
  {
    "Attack": 50,
    "Defense": 77,
    "HP": 50,
    "Special_Atk": 95,
    "Special_Def": 77,
    "Speed": 91,
    "Total": 440,
    "Type1": "Electric",
    "Type2": "Ghost"
  },
  {
    "Attack": 100,
    "Defense": 120,
    "HP": 100,
    "Special_Atk": 150,
    "Special_Def": 120,
    "Speed": 90,
    "Total": 680,
    "Type1": "Steel",
    "Type2": "Dragon"
  },
  {
    "Attack": 67,
    "Defense": 85,
    "HP": 60,
    "Special_Atk": 77,
    "Special_Def": 75,
    "Speed": 116,
    "Total": 480,
    "Type1": "Grass",
    "Type2": "Fairy"
  },
  {
    "Attack": 117,
    "Defense": 80,
    "HP": 95,
    "Special_Atk": 65,
    "Special_Def": 70,
    "Speed": 92,
    "Total": 519,
    "Type1": "Ground",
    "Type2": "Dark"
  },
  {
    "Attack": 160,
    "Defense": 55,
    "HP": 105,
    "Special_Atk": 30,
    "Special_Def": 55,
    "Speed": 135,
    "Total": 540,
    "Type1": "Ice",
    "Type2": "Fire"
  },
  {
    "Attack": 30,
    "Defense": 105,
    "HP": 105,
    "Special_Atk": 140,
    "Special_Def": 105,
    "Speed": 55,
    "Total": 540,
    "Type1": "Fire",
    "Type2": "Psychic"
  },
  {
    "Attack": 75,
    "Defense": 70,
    "HP": 50,
    "Special_Atk": 35,
    "Special_Def": 70,
    "Speed": 48,
    "Total": 348,
    "Type1": "Fighting",
    "Type2": "Dark"
  },
  {
    "Attack": 60,
    "Defense": 70,
    "HP": 100,
    "Special_Atk": 85,
    "Special_Def": 105,
    "Speed": 60,
    "Total": 480,
    "Type1": "Water",
    "Type2": "Ghost"
  },
  {
    "Attack": 55,
    "Defense": 85,
    "HP": 38,
    "Special_Atk": 30,
    "Special_Def": 65,
    "Speed": 30,
    "Total": 303,
    "Type1": "Ground",
    "Type2": "Ghost"
  },
  {
    "Attack": 60,
    "Defense": 40,
    "HP": 35,
    "Special_Atk": 85,
    "Special_Def": 40,
    "Speed": 70,
    "Total": 330,
    "Type1": "Normal",
    "Type2": "Ghost"
  },
  {
    "Attack": 60,
    "Defense": 50,
    "HP": 60,
    "Special_Atk": 40,
    "Special_Def": 50,
    "Speed": 75,
    "Total": 335,
    "Type1": "Normal",
    "Type2": "Grass"
  },
  {
    "Attack": 47,
    "Defense": 50,
    "HP": 50,
    "Special_Atk": 57,
    "Special_Def": 50,
    "Speed": 65,
    "Total": 319,
    "Type1": "Bug",
    "Type2": "Electric"
  },
  {
    "Attack": 94,
    "Defense": 131,
    "HP": 74,
    "Special_Atk": 54,
    "Special_Def": 116,
    "Speed": 20,
    "Total": 489,
    "Type1": "Grass",
    "Type2": "Steel"
  },
  {
    "Attack": 125,
    "Defense": 100,
    "HP": 65,
    "Special_Atk": 60,
    "Special_Def": 70,
    "Speed": 70,
    "Total": 490,
    "Type1": "Dark",
    "Type2": "Steel"
  },
  {
    "Attack": 66,
    "Defense": 84,
    "HP": 109,
    "Special_Atk": 81,
    "Special_Def": 99,
    "Speed": 32,
    "Total": 471,
    "Type1": "Ground",
    "Type2": "Electric"
  },
  {
    "Attack": 65,
    "Defense": 50,
    "HP": 52,
    "Special_Atk": 45,
    "Special_Def": 50,
    "Speed": 38,
    "Total": 300,
    "Type1": "Dark",
    "Type2": "Dragon"
  },
  {
    "Attack": 129,
    "Defense": 90,
    "HP": 91,
    "Special_Atk": 72,
    "Special_Def": 90,
    "Speed": 108,
    "Total": 580,
    "Type1": "Rock",
    "Type2": "Fighting"
  },
  {
    "Attack": 60,
    "Defense": 65,
    "HP": 85,
    "Special_Atk": 135,
    "Special_Def": 105,
    "Speed": 100,
    "Total": 550,
    "Type1": "Fire",
    "Type2": "Bug"
  },
  {
    "Attack": 170,
    "Defense": 100,
    "HP": 125,
    "Special_Atk": 120,
    "Special_Def": 90,
    "Speed": 95,
    "Total": 700,
    "Type1": "Dragon",
    "Type2": "Ice"
  },
  {
    "Attack": 56,
    "Defense": 77,
    "HP": 85,
    "Special_Atk": 50,
    "Special_Def": 77,
    "Speed": 78,
    "Total": 423,
    "Type1": "Normal",
    "Type2": "Ground"
  },
  {
    "Attack": 128,
    "Defense": 90,
    "HP": 100,
    "Special_Atk": 77,
    "Special_Def": 77,
    "Speed": 128,
    "Total": 600,
    "Type1": "Normal",
    "Type2": "Fighting"
  },
  {
    "Attack": 59,
    "Defense": 50,
    "HP": 77,
    "Special_Atk": 67,
    "Special_Def": 63,
    "Speed": 46,
    "Total": 362,
    "Type1": "Ice",
    "Type2": "Rock"
  },
  {
    "Attack": 50,
    "Defense": 140,
    "HP": 60,
    "Special_Atk": 50,
    "Special_Def": 140,
    "Speed": 60,
    "Total": 500,
    "Type1": "Steel",
    "Type2": "Ghost"
  },
  {
    "Attack": 55,
    "Defense": 52,
    "HP": 62,
    "Special_Atk": 109,
    "Special_Def": 94,
    "Speed": 109,
    "Total": 481,
    "Type1": "Electric",
    "Type2": "Normal"
  },
  {
    "Attack": 121,
    "Defense": 119,
    "HP": 82,
    "Special_Atk": 69,
    "Special_Def": 59,
    "Speed": 71,
    "Total": 521,
    "Type1": "Rock",
    "Type2": "Dragon"
  },
  {
    "Attack": 50,
    "Defense": 58,
    "HP": 62,
    "Special_Atk": 73,
    "Special_Def": 54,
    "Speed": 72,
    "Total": 369,
    "Type1": "Fire",
    "Type2": "Normal"
  },
  {
    "Attack": 54,
    "Defense": 53,
    "HP": 53,
    "Special_Atk": 37,
    "Special_Def": 46,
    "Speed": 45,
    "Total": 288,
    "Type1": "Dark",
    "Type2": "Psychic"
  },
  {
    "Attack": 75,
    "Defense": 90,
    "HP": 65,
    "Special_Atk": 97,
    "Special_Def": 123,
    "Speed": 44,
    "Total": 494,
    "Type1": "Poison",
    "Type2": "Dragon"
  },
  {
    "Attack": 58,
    "Defense": 57,
    "HP": 67,
    "Special_Atk": 81,
    "Special_Def": 67,
    "Speed": 101,
    "Total": 431,
    "Type1": "Electric",
    "Type2": "Fairy"
  },
  {
    "Attack": 110,
    "Defense": 76,
    "HP": 85,
    "Special_Atk": 65,
    "Special_Def": 82,
    "Speed": 56,
    "Total": 474,
    "Type1": "Grass",
    "Type2": "Ghost"
  },
  {
    "Attack": 70,
    "Defense": 92,
    "HP": 68,
    "Special_Atk": 50,
    "Special_Def": 132,
    "Speed": 42,
    "Total": 454,
    "Type1": "Bug",
    "Type2": "Water"
  },
  {
    "Attack": 132,
    "Defense": 77,
    "HP": 97,
    "Special_Atk": 62,
    "Special_Def": 67,
    "Speed": 43,
    "Total": 478,
    "Type1": "Fighting",
    "Type2": "Ice"
  },
  {
    "Attack": 45,
    "Defense": 40,
    "HP": 40,
    "Special_Atk": 55,
    "Special_Def": 40,
    "Speed": 84,
    "Total": 304,
    "Type1": "Bug",
    "Type2": "Fairy"
  },
  {
    "Attack": 44,
    "Defense": 40,
    "HP": 48,
    "Special_Atk": 71,
    "Special_Def": 40,
    "Speed": 77,
    "Total": 320,
    "Type1": "Poison",
    "Type2": "Fire"
  },
  {
    "Attack": 90,
    "Defense": 80,
    "HP": 55,
    "Special_Atk": 50,
    "Special_Def": 105,
    "Speed": 96,
    "Total": 476,
    "Type1": "Ghost",
    "Type2": "Fairy"
  },
  {
    "Attack": 60,
    "Defense": 85,
    "HP": 78,
    "Special_Atk": 135,
    "Special_Def": 91,
    "Speed": 36,
    "Total": 485,
    "Type1": "Normal",
    "Type2": "Dragon"
  },
  {
    "Attack": 110,
    "Defense": 125,
    "HP": 75,
    "Special_Atk": 100,
    "Special_Def": 105,
    "Speed": 85,
    "Total": 600,
    "Type1": "Dragon",
    "Type2": "Fighting"
  },
  {
    "Attack": 53,
    "Defense": 47,
    "HP": 109,
    "Special_Atk": 127,
    "Special_Def": 131,
    "Speed": 103,
    "Total": 570,
    "Type1": "Rock",
    "Type2": "Poison"
  },
  {
    "Attack": 78,
    "Defense": 135,
    "HP": 60,
    "Special_Atk": 91,
    "Special_Def": 85,
    "Speed": 36,
    "Total": 485,
    "Type1": "Fire",
    "Type2": "Dragon"
  },
  {
    "Attack": 113,
    "Defense": 109,
    "HP": 97,
    "Special_Atk": 157,
    "Special_Def": 127,
    "Speed": 77,
    "Total": 680,
    "Type1": "Psychic",
    "Type2": "Ghost"
  },
  {
    "Attack": 35,
    "Defense": 80,
    "HP": 50,
    "Special_Atk": 50,
    "Special_Def": 90,
    "Speed": 30,
    "Total": 335,
    "Type1": "Bug",
    "Type2": "Psychic"
  },
  {
    "Attack": 38,
    "Defense": 35,
    "HP": 40,
    "Special_Atk": 54,
    "Special_Def": 35,
    "Speed": 40,
    "Total": 242,
    "Type1": "Electric",
    "Type2": "Poison"
  },
  {
    "Attack": 45,
    "Defense": 30,
    "HP": 45,
    "Special_Atk": 55,
    "Special_Def": 40,
    "Speed": 50,
    "Total": 265,
    "Type1": "Dark",
    "Type2": "Fairy"
  },
  {
    "Attack": 100,
    "Defense": 90,
    "HP": 90,
    "Special_Atk": 80,
    "Special_Def": 70,
    "Speed": 75,
    "Total": 505,
    "Type1": "Electric",
    "Type2": "Dragon"
  },
  {
    "Attack": 25,
    "Defense": 35,
    "HP": 30,
    "Special_Atk": 45,
    "Special_Def": 30,
    "Speed": 20,
    "Total": 185,
    "Type1": "Ice",
    "Type2": "Bug"
  },
  {
    "Attack": 95,
    "Defense": 58,
    "HP": 58,
    "Special_Atk": 70,
    "Special_Def": 58,
    "Speed": 97,
    "Total": 436,
    "Type1": "Electric",
    "Type2": "Dark"
  },
  {
    "Attack": 50,
    "Defense": 150,
    "HP": 50,
    "Special_Atk": 50,
    "Special_Def": 150,
    "Speed": 50,
    "Total": 500,
    "Type1": "Rock",
    "Type2": "Fairy"
  }
]
